{"uid": 5866, "pageId": "artwork:other", "title": "\u041d\u0435\u0440\u0430\u0441\u0441\u043e\u0440\u0442\u0438\u0440\u043e\u0432\u0430\u043d\u043d\u044b\u0435 \u0440\u0430\u0431\u043e\u0442\u044b \u0434\u0440\u0443\u0433\u0438\u0445 \u0430\u0432\u0442\u043e\u0440\u043e\u0432", "source": "[[include component:easy-gallery\n|wide=true\n|header=SCP-RU ArtWork-hub\n|subheader=\u0420\u0430\u0431\u043e\u0442\u044b \u0434\u0440\u0443\u0433\u0438\u0445 \u0430\u0432\u0442\u043e\u0440\u043e\u0432\n]]\n\n[[>]]\n[[module Rate]]\n[[/>]]\n\n[[div class=\"ez-gallery\"]]\n\n[[div]]\n[[include component:image-zoom name=http://scpfoundation.net/local--files/artwork%3Aother/1340-ru |caption=SCP-1340-RU (\u0414\u0438\u043d \u0414\u0436\u0435\u0444\u0444\u0435\u0440\u0441\u043e\u043d, \u043f\u0440\u0438\u0437\u0435\u0440 \u0430\u0440\u0442-\u043a\u043e\u043d\u043a\u0443\u0440\u0441\u0430 \u21161)|width=500px]]\n[[/div]]\n[[div]]\n[[include component:image-zoom name=http://scpfoundation.net/local--files/artwork%3Aother/1204-ru.jpg |caption=SCP-1204-RU (\u041a\u0430\u0442\u044f \u0413\u0430\u043f\u043e\u043d\u043e\u0432\u0430)|width=400px]]\n[[/div]]\n\n\n[[div]]\n[[include component:image-zoom name=http://scpfoundation.net/local--files/artwork%3Aother/1338-ru.jpg |caption=SCP-1338-RU (\u0420\u043e\u0437\u0430 \u041a\u0440\u0435\u043c\u043b\u0435\u0432\u0430)|width=500px]]\n[[/div]]\n[[div]]\n[[include component:image-zoom name=http://scpfoundation.net/local--files/artwork%3Aother/1110-ru.jpg|caption=SCP-1110-RU (\u0414\u043c\u0438\u0442\u0440\u0438\u0439 \u041e\u0440\u043b\u043e\u0432)|width=400px]]\n[[/div]]\n\n\n[[div]]\n[[include component:image-zoom name=http://scpfoundation.net/local--files/artwork%3Aother/1068-ru.jpg |caption=SCP-1068-RU (\u0412\u0430\u043b\u0435\u043d\u0442\u0438\u043d\u0430 \u041a\u0435\u043b\u043b\u0435\u0440\u043c\u0430\u043d, \u043f\u0440\u0438\u0437\u0435\u0440 \u0430\u0440\u0442-\u043a\u043e\u043d\u043a\u0443\u0440\u0441\u0430 \u21161)|width=500px]]\n[[/div]]\n[[div]]\n[[include component:image-zoom name=http://scpfoundation.net/local--files/artwork%3Aother/1239-ru.jpg |caption=SCP-1239-RU (\u0410\u043b\u0438\u0441\u0430 \u041c\u043e\u0440\u0430\u043d)|width=400px]]\n[[/div]]\n\n\n[[div]]\n[[include component:image-zoom name=http://scpfoundation.net/local--files/artwork%3Aother/1347-ru.jpg |caption=SCP-1347-RU (\u041b\u043e\u043d\u0435\u043b\u0438 \u0416\u0430\u043a, \u0444\u043b\u0443\u043e\u0440\u0435\u0441\u0446\u0435\u043d\u0442\u043d\u044b\u0435 \u043a\u0440\u0430\u0441\u043a\u0438)|width=500px]]\n[[/div]]\n[[div]]\n[[include component:image-zoom name=http://scpfoundation.net/local--files/artwork%3Aother/1068-ru-2.jpg |caption=SCP-1068-RU (\u0412\u0438\u043a\u0442\u043e\u0440 \u0422\u0438\u0440\u0441\u043e\u0432)|width=300px]]\n[[/div]]\n\n\n[[div]]\n[[include component:image-zoom name=http://scpfoundation.net/local--files/artwork%3Aother/1366-ru |caption=SCP-1366-RU (\u0421\u043e\u043d\u044f \u0420\u043e\u043c\u0430\u0448\u043e\u0432\u0430, \u043f\u043e\u0431\u0435\u0434\u0438\u0442\u0435\u043b\u044c \u0430\u0440\u0442-\u043a\u043e\u043d\u043a\u0443\u0440\u0441\u0430 \u21162)|width=300px]]\n[[/div]]\n[[div]]\n[[include component:image-zoom name=http://scpfoundation.net/local--files/artwork%3Aother/ubermensch |caption=\"\u0411\u043e\u0433 \u0443\u043c\u0435\u0440: \u0442\u0435\u043f\u0435\u0440\u044c \u0445\u043e\u0442\u0438\u043c \u043c\u044b, \u0447\u0442\u043e\u0431\u044b \u0436\u0438\u043b \u0441\u0432\u0435\u0440\u0445\u0447\u0435\u043b\u043e\u0432\u0435\u043a\" (\u0415\u0432\u0433\u0435\u043d\u0438\u044f \u0428\u0438\u043f\u043e\u0432\u043d\u0438\u043a, \u0443\u0447\u0430\u0441\u0442\u043d\u0438\u043a \u0430\u0440\u0442-\u043a\u043e\u043d\u043a\u0443\u0440\u0441\u0430 \u21162, \u0430\u0432\u0442\u043e\u0440 DocFelix)|width=300px]]\n[[/div]]\n\n[[/div]]", "tags": ["\u0441\u0442\u0440\u0443\u043a\u0442\u0443\u0440\u0430:\u043f\u0440\u043e\u0447\u0438\u0435_\u043c\u0430\u0442\u0435\u0440\u0438\u0430\u043b\u044b"], "parent": "artwork:russian-art-hub", "locked": false}