{"uid": 10057, "pageId": "fragment:djkaktus-s-proposal-iii-9", "title": "9", "source": "[[include theme:black-highlighter-theme]]\n[[include theme:ouroborous-theme]]\n------\n\n[[=]]\n[[image \u041e5-10Page1.png]]\n@@@@\n[[image \u041e5-10Page2.png]]\n@@@@\n[[image \u041e5-10Page3.png]]\n@@@@\n[[image \u041e5-10Page4.png]]\n@@@@\n[[image \u041e5-10Page5.png]]\n@@@@\n-----\n\n**[/djkaktus-s-proposal-iii/offset/1 \u041d\u0410\u0417\u0410\u0414]**\n[[/=]]", "tags": [], "parent": "djkaktus-s-proposal-iii", "locked": false}